secretpkg555/__init__.py
secretpkg555/api.py
secretpkg555/core_logic.cp312-win_amd64.pyd
secretpkg555/core_logic.cp39-win_amd64.pyd
pykitos-0.1.0.dist-info/METADATA
pykitos-0.1.0.dist-info/WHEEL
pykitos-0.1.0.dist-info/top_level.txt
pykitos-0.1.0.dist-info/RECORD
