Metadata-Version: 2.4
Name: pykitos
Version: 0.1.0
Summary: 简单的计算包 - 核心逻辑二进制保护
Author-email: None555 <none555@example.com>
License: MIT
Keywords: calculation,binary,nuitka,protected
Classifier: Development Status :: 3 - Alpha
Classifier: Intended Audience :: Developers
Classifier: License :: OSI Approved :: MIT License
Classifier: Programming Language :: Python :: 3.8
Classifier: Operating System :: OS Independent
Classifier: Topic :: Software Development :: Libraries :: Python Modules
Requires-Python: >=3.8
